labelx/__init__.py
labelx/__version__.py
labelx/api_manager.py
labelx/app.py
labelx/badges.yaml
labelx/config_manager.py
labelx/controller.py
labelx/labels.yaml
labelx/settings.py
labelx/utils.py
labelx-2.3.1.dist-info/AUTHORS.rst
labelx-2.3.1.dist-info/LICENSE
labelx-2.3.1.dist-info/METADATA
labelx-2.3.1.dist-info/WHEEL
labelx-2.3.1.dist-info/entry_points.txt
labelx-2.3.1.dist-info/top_level.txt
labelx-2.3.1.dist-info/RECORD
