Metadata-Version: 2.1
Name: labelx
Version: 2.3.1
Summary: Label Creator for GitLab Projects.
Home-page: https://github.com/dalwar23/labelxg
Author: Dalwar Hossain
Author-email: dalwar23@pm.me
License: GNU General Public License v3
Keywords: labelx
Platform: UNKNOWN
Classifier: Development Status :: 4 - Beta
Classifier: Environment :: Console
Classifier: Intended Audience :: Developers
Classifier: License :: OSI Approved :: GNU General Public License v3 (GPLv3)
Classifier: Natural Language :: English
Classifier: Programming Language :: Python :: 3
Classifier: Programming Language :: Python :: 3.6
Classifier: Programming Language :: Python :: 3.7
Classifier: Programming Language :: Python :: 3.8
Classifier: Programming Language :: Python :: 3.9
Classifier: Programming Language :: Python :: 3.10
Requires-Python: >=3.6
License-File: LICENSE
License-File: AUTHORS.rst
Requires-Dist: Click (>=8.0.4)
Requires-Dist: requests (>=2.27.1)
Requires-Dist: colorama (>=0.4.4)
Requires-Dist: pyyaml (>=6.0.0)
